{
  "unversionedId": "records/delete-record",
  "id": "records/delete-record",
  "title": "Delete record",
  "description": "Delete Record (Single)",
  "source": "@site/docs/070.records/040.delete-record.md",
  "sourceDirName": "070.records",
  "slug": "/records/delete-record",
  "permalink": "/records/delete-record",
  "draft": false,
  "editUrl": "https://github.com/nocodb/nocodb/tree/develop/packages/noco-docs/docs/docs/070.records/040.delete-record.md",
  "tags": [],
  "version": "current",
  "sidebarPosition": 40,
  "frontMatter": {
    "title": "Delete record",
    "keywords": [
      "NocoDB delete record",
      "delete record",
      "delete row",
      "delete rows"
    ]
  },
  "sidebar": "tutorialSidebar",
  "previous": {
    "title": "Expanded form",
    "permalink": "/records/expanded-record"
  },
  "next": {
    "title": "Actions on record",
    "permalink": "/records/actions-on-record"
  }
}