{
  "unversionedId": "views/delete-view",
  "id": "views/delete-view",
  "title": "Delete view",
  "description": "Learn how to delete a view in NocoDB.",
  "source": "@site/docs/080.views/050.delete-view.md",
  "sourceDirName": "080.views",
  "slug": "/views/delete-view",
  "permalink": "/views/delete-view",
  "draft": false,
  "editUrl": "https://github.com/nocodb/nocodb/tree/develop/packages/noco-docs/docs/docs/080.views/050.delete-view.md",
  "tags": [
    {
      "label": "views",
      "permalink": "/tags/views"
    },
    {
      "label": "delete view",
      "permalink": "/tags/delete-view"
    }
  ],
  "version": "current",
  "sidebarPosition": 50,
  "frontMatter": {
    "title": "Delete view",
    "description": "Learn how to delete a view in NocoDB.",
    "tags": [
      "views",
      "delete view"
    ],
    "keywords": [
      "NocoDB view",
      "delete view",
      "view administration",
      "view organization"
    ]
  },
  "sidebar": "tutorialSidebar",
  "previous": {
    "title": "Share View",
    "permalink": "/views/share-view"
  },
  "next": {
    "title": "Actions on view",
    "permalink": "/views/actions-on-view"
  }
}