{
  "label": "base actions",
  "permalink": "/tags/base-actions",
  "allTagsPath": "/tags",
  "count": 2,
  "items": [
    {
      "id": "bases/actions-on-base",
      "title": "Actions on base",
      "description": "Actions you can perform on a base in NocoDB: Rename, duplicate, delete, star a base.",
      "permalink": "/bases/actions-on-base"
    },
    {
      "id": "bases/base-overview",
      "title": "Base overview",
      "description": "This article explains the concept of bases in NocoDB.",
      "permalink": "/bases/base-overview"
    }
  ]
}